{
  "indexes": [
    {
      "collectionGroup": "lifeLogs",
      "queryScope": "COLLECTION",
      "fields": [
        {
          "fieldPath": "startAt",
          "order": "ASCENDING"
        },
        {
          "fieldPath": "endAt",
          "order": "ASCENDING"
        }
      ]
    },
    {
      "collectionGroup": "lifeLogTreeNodes",
      "queryScope": "COLLECTION",
      "fields": [
        {
          "fieldPath": "parentId",
          "order": "ASCENDING"
        },
        {
          "fieldPath": "order",
          "order": "ASCENDING"
        }
      ]
    },
    {
      "collectionGroup": "pocFirestoreIndexOrderItems",
      "queryScope": "COLLECTION",
      "fields": [
        {
          "fieldPath": "startAt",
          "order": "ASCENDING"
        },
        {
          "fieldPath": "endAt",
          "order": "ASCENDING"
        }
      ]
    }
  ],
  "fieldOverrides": []
}
